constants.py
main.py
test_main.py
py_pomodoro_cli-0.1.4.dist-info/METADATA
py_pomodoro_cli-0.1.4.dist-info/WHEEL
py_pomodoro_cli-0.1.4.dist-info/entry_points.txt
py_pomodoro_cli-0.1.4.dist-info/top_level.txt
py_pomodoro_cli-0.1.4.dist-info/RECORD
