Metadata-Version: 2.4
Name: py-pomodoro-cli
Version: 0.1.4
Summary: A simple and beautiful Pomodoro CLI tool built with Typer and Rich.
Author-email: Wayne Fagan <hello@waynefagan.dev>
Project-URL: Homepage, https://gitlab.com/Wayne-F/py-pomodoro-cli
Project-URL: Repository, https://gitlab.com/Wayne-F/py-pomodoro-cli
Keywords: pomodoro,cli,typer,rich
Classifier: Development Status :: 4 - Beta
Classifier: Intended Audience :: Developers
Classifier: Topic :: Software Development :: Build Tools
Classifier: Programming Language :: Python :: 3
Classifier: Programming Language :: Python :: 3.9
Requires-Python: >=3.9
Requires-Dist: typer>=0.12.3
Requires-Dist: rich>=13.7.1
